src/FIFO.py
src/LIFO.py
src/Link.py
src/Node.py
src/Tree.py
src/__init__.py
structure_tool-1.0.0.dist-info/LICENSE
structure_tool-1.0.0.dist-info/METADATA
structure_tool-1.0.0.dist-info/WHEEL
structure_tool-1.0.0.dist-info/top_level.txt
structure_tool-1.0.0.dist-info/RECORD
