Metadata-Version: 2.1
Name: structure-tool
Version: 1.0.0
Summary: 一个提供多个结构的Python项目
Home-page: https://github.com/yufeng6661666/structure
Author: yufeng6661666
Author-email: android123r@outlook.com
Classifier: Programming Language :: Python :: 3
Classifier: License :: OSI Approved :: MIT License
Classifier: Operating System :: OS Independent
Requires-Python: >=3.0
License-File: LICENSE
